quaternionmath/__init__.py
quaternionmath/main.py
quaternionmath-1.0.1.dist-info/LICENSE
quaternionmath-1.0.1.dist-info/METADATA
quaternionmath-1.0.1.dist-info/WHEEL
quaternionmath-1.0.1.dist-info/top_level.txt
quaternionmath-1.0.1.dist-info/RECORD
